python_gitfix/main.py
python_gitfix/rag.py
python_gitfix/schemas.py
python_gitfix/system_prompt.txt
python_gitfix-0.1.2.dist-info/METADATA
python_gitfix-0.1.2.dist-info/WHEEL
python_gitfix-0.1.2.dist-info/entry_points.txt
python_gitfix-0.1.2.dist-info/RECORD
