Metadata-Version: 2.1
Name: python-gitfix
Version: 0.1.2
Summary: 
Author: Devansh Singh
Author-email: devanshamity@gmail.com
Requires-Python: >=3.10,<4.0
Classifier: Programming Language :: Python :: 3
Classifier: Programming Language :: Python :: 3.10
Classifier: Programming Language :: Python :: 3.11
Classifier: Programming Language :: Python :: 3.12
Requires-Dist: chromadb (>=0.5.3,<0.6.0)
Requires-Dist: httpx (>=0.27.0,<0.28.0)
Requires-Dist: pydantic (>=2.8.2,<3.0.0)
Requires-Dist: pygments (>=2.18.0,<3.0.0)
Requires-Dist: python-dotenv (>=1.0.1,<2.0.0)
Requires-Dist: rich (>=13.7.1,<14.0.0)
Requires-Dist: simple-term-menu (>=1.6.4,<2.0.0)
